{
    "description": "This is a quick introduction to Universal (isomorphic) JavaScript support for Angular 2. The Angular Universal project aims to add support for server side rendering to Angular 2 apps. In other words, with Universal you will be able to render your Angular 2 application both on the client and the server. If you're curious and want to know and see how Angular 2 is handling universality then don't miss this talk.",
    "recorded": "2016-10-25",
    "speakers": [],
    "tags": [],
    "thumbnail_url": "https://i.ytimg.com/vi/faWCLmYsFQ8/hqdefault.jpg",
    "title": "Wassim Chegham (@manekinekko): Getting Universal with Angular 2 at ng-europe 2016",
    "videos": [
        {
            "code": "faWCLmYsFQ8",
            "type": "youtube"
        }
    ]
}