{"description": "\u5b98\u65b9\u7db2\u7ad9\uff1ahttp://2015.rubyconf.tw", "event": {"name": "Ruby Conf Taiwan 2015", "nickname": "rubyconf-taiwan-2015", "twitter": "rubyconftw", "url": "http://2015.rubyconf.tw/"}, "favorite": "0", "file_date": "2016-12-03", "filename": "rubyconf-taiwan-2015-day1-r2-03-xu-si-kai-szu-kai-hsu-brucehsuevolution-of-gobies", "length": "24:46", "likes": "0", "recorded": "2015-09-11", "short_description": "\u5b98\u65b9\u7db2\u7ad9\uff1ahttp://2015.rubyconf.tw", "speaker_twitters": "", "speakers": {}, "tags": [], "thumbnail_url": "https://i.ytimg.com/vi/9m4FzGPtGig/hqdefault.jpg", "title": "RubyConf Taiwan 2015-Day1 R2 03 \u8a31\u65af\u51f1  Szu Kai Hsu brucehsu\uff1aEvolution of Gobies", "tweet_video": "RubyConf%20Taiwan%202015-Day1%20R2%2003%20%E8%A8%B1%E6%96%AF%E5%87%B1%20%20Szu%20Kai%20Hsu%20brucehsu%EF%BC%9AEvolution%20of%20Gobies%20https%3A//codeandtalk.com/v/rubyconf-taiwan-2015/rubyconf-taiwan-2015-day1-r2-03-xu-si-kai-szu-kai-hsu-brucehsuevolution-of-gobies%20presented%20%40rubyconftw", "videos": [{"code": "9m4FzGPtGig", "type": "youtube"}], "views": "15"}