{
    "description": "Apache In Science",
    "favorite": "0",
    "length": "44:31",
    "likes": "1",
    "recorded": "2013-02-27",
    "speakers": [
        "richard-ullman",
        "peyush-jain"
    ],
    "tags": [],
    "thumbnail_url": "https://i.ytimg.com/vi/s_AkUFk_hrU/hqdefault.jpg",
    "title": "Case Study: Apache OODT Framework Application for Support to the Joint Polar Satellite System (JPSS)",
    "videos": [
        {
            "code": "s_AkUFk_hrU",
            "type": "youtube"
        }
    ],
    "views": "167"
}