{"description": "Building Your Own Toolkit For Rational Inquiry", "event": {"name": "Ruby Conf Portugal", "nickname": "rubyconf-portugal-2016", "twitter": "rubyconfpt", "url": "http://rubyconf.pt/"}, "favorite": "0", "file_date": "2017-01-05", "filename": "kerri-miller-crescent-wrenches-and-debuggers-rubyconf-portugal16", "length": "45:54", "likes": "2", "recorded": "2016-10-27", "short_description": "Building Your Own Toolkit For Rational Inquiry", "speaker_twitters": " @kerrizor", "speakers": {"kerri-miller": {"episodes": [], "hosting": [], "info": {"country": "Seattle, WA, USA", "github": "kerrizor", "home": "http://kerrizor.com/", "name": "Kerri Miller", "twitter": "kerrizor"}, "videos": [{"event": {"name": "Open Source Bridge 2016", "nickname": "opensourcebridge-2015", "twitter": "osbridge", "url": "http://opensourcebridge.org/y2015/"}, "filename": "osb-2015-software-archeology-and-the-code-of-doom-kerri-miller", "recorded": "2015-06-23", "thumbnail_url": "https://i.ytimg.com/vi/2YlO9MGlrXY/hqdefault.jpg", "title": "Software Archeology and The Code Of Doom"}, {"event": {"name": "Ruby Conf Portugal", "nickname": "rubyconf-portugal-2016", "twitter": "rubyconfpt", "url": "http://rubyconf.pt/"}, "filename": "kerri-miller-crescent-wrenches-and-debuggers-rubyconf-portugal16", "recorded": "2016-10-27", "thumbnail_url": "https://i.ytimg.com/vi/JN4LqjPVHGc/hqdefault.jpg", "title": "Crescent Wrenches and Debuggers"}, {"event": {"name": "Ruby Conf Portugal", "nickname": "rubyconf-portugal-2016", "twitter": "rubyconfpt", "url": "http://rubyconf.pt/"}, "filename": "panel-martin-fowler-kerri-miller-aaron-patterson-yehuda-katz-hiro-asari-rubyconf-pt16", "recorded": "2016-10-27", "thumbnail_url": "https://i.ytimg.com/vi/jATImleUwVY/hqdefault.jpg", "title": "Panel"}]}}, "tags": [], "thumbnail_url": "https://i.ytimg.com/vi/JN4LqjPVHGc/hqdefault.jpg", "title": "Crescent Wrenches and Debuggers", "tweet_video": "Crescent%20Wrenches%20and%20Debuggers%20https%3A//codeandtalk.com/v/rubyconf-portugal-2016/kerri-miller-crescent-wrenches-and-debuggers-rubyconf-portugal16%20presented%20%40rubyconfpt%20by%20%40kerrizor", "videos": [{"code": "JN4LqjPVHGc", "type": "youtube"}], "views": "47"}