{
    "description": "Diving Deep Into Browserify - Yoshua Wuyts\n\nBrowserify has been one of the staple tools for packaging javascript and shipping it to the browser. In this talk Yosh will explain browserify's internals, the current state of tooling and the path that's currently set for the future.",
    "favorite": "0",
    "length": "22:07",
    "likes": "7",
    "recorded": "2016-11-29",
    "speakers": [],
    "tags": [],
    "thumbnail_url": "https://i.ytimg.com/vi/-LCLeV7swkA/hqdefault.jpg",
    "title": "Diving Deep Into Browserify - Yoshua Wuyts",
    "videos": [
        {
            "code": "-LCLeV7swkA",
            "type": "youtube"
        }
    ],
    "views": "394"
}