{
    "description": "ES modules form a finalised specification for writing modular code in JavaScript, yet still have to be fully adopted by browsers. We'll look at how ES modules are being supported in browsers and describe some of the implementation questions that still remain, including exploring some of the possibilities of future modular workflows for the browser.",
    "favorite": "0",
    "length": "42:13",
    "likes": "0",
    "recorded": "2016-06-30",
    "speakers": [
        "guy-bedford"
    ],
    "tags": [],
    "thumbnail_url": "https://i.ytimg.com/vi/cRSBi1EAOCo/hqdefault.jpg",
    "title": "Dynamic Linking in the Browser",
    "videos": [
        {
            "code": "cRSBi1EAOCo",
            "type": "youtube"
        }
    ],
    "views": "261"
}