{
    "description": "The NES remains one of the most loved entertainment consoles on the planet. Homebrew games are still being made in 2016. But why not help the process with some build tools?",
    "recorded": "2016-07-03",
    "speakers": [
        "fritz-van-deventer"
    ],
    "thumbnail_url": "https://i.ytimg.com/vi/WRSRVdLQ_-k/hqdefault.jpg",
    "title": "Super MarioScript: Tools and Tips for NES development",
    "videos": [
        {
            "code": "WRSRVdLQ_-k",
            "type": "youtube"
        }
    ]
}