{"description": "When developing a new product, developers are naturally attracted to using the newest technology: Node! Go! Clojure! React! Elixir! Mongo! Dynamo! But is that really a wise choice? This talk will share experiences from building products with the latest and greatest technology stacks and the risks it brings to the project.", "event": {"name": "PolyConf - Polyglot Programmers Unite - 2016", "nickname": "polyconf-2016", "twitter": "", "url": "http://polyconf.com/"}, "favorite": "0", "file_date": "2016-12-03", "filename": "polyconf-16-pick-your-battles-zef-hemel", "length": "30:02", "likes": "8", "recorded": "2016-06-30", "short_description": "When developing a new product, developers are naturally attracted to using the newest technology: Node! Go! Clojure! React! Elix", "speaker_twitters": " @zef", "speakers": {"zef-hemel": {"episodes": [], "hosting": [], "info": {"country": "Poznan, Poland", "github": "zefhemel", "home": "https://zef.me/", "name": "Zef Hemel", "twitter": "zef"}, "videos": [{"event": {"name": "PolyConf - Polyglot Programmers Unite - 2016", "nickname": "polyconf-2016", "twitter": "", "url": "http://polyconf.com/"}, "filename": "polyconf-16-pick-your-battles-zef-hemel", "recorded": "2016-06-30", "thumbnail_url": "https://i.ytimg.com/vi/J_44tCwpChY/hqdefault.jpg", "title": "Pick Your Battles"}]}}, "tags": [], "thumbnail_url": "https://i.ytimg.com/vi/J_44tCwpChY/hqdefault.jpg", "title": "Pick Your Battles", "tweet_video": "Pick%20Your%20Battles%20https%3A//codeandtalk.com/v/polyconf-2016/polyconf-16-pick-your-battles-zef-hemel%20by%20%40zef", "videos": [{"code": "J_44tCwpChY", "type": "youtube"}], "views": "320"}