{
    "description": "Inscreva-se.\nhttps://goo.gl/NfsjjA\n\nLaborat\u00f3rios de Inform\u00e1tica, banda Larga e Comunidade Escolar\nTrilha: Ecossistema - Cultura, Filosofia, e Pol\u00edtica\nAutores:\nJos\u00e9 Francisco Nunes Fernandez\nApresenta\u00e7\u00e3o:\nDia 14 \u00e0s 18:00 na sala 41A (60 minutos)  v\u00eddeo\nDescri\u00e7\u00e3o:  Como foi a evolu\u00e7\u00e3o do n\u00famero de laborat\u00f3rios de Inform\u00e1tica nos \u00faltimos 6 anos no RS e qual o papel do software livre neste processo. Utilizando para   tanto uma compila\u00e7\u00e3o dos dados oficiais do INEPE.",
    "favorite": "0",
    "length": "48:35",
    "likes": "0",
    "recorded": "2016-07-13",
    "speakers": [],
    "tags": [],
    "thumbnail_url": "https://i.ytimg.com/vi/eKTdPqdPpYY/hqdefault.jpg",
    "title": "Laborat\u00f3rios de Inform\u00e1tica, banda Larga e Comunidade Escolar",
    "videos": [
        {
            "code": "eKTdPqdPpYY",
            "type": "youtube"
        }
    ],
    "views": "28"
}