{
    "description": "Inscreva-se.\nhttps://goo.gl/NfsjjA\n\nPrograma Minha Escola Mais Inteligente\nTrilha: Educação - Inclusão Digital\nAutores:\nVagner Vieira Schmitt\nApresentação:\nDia 13 às 13:00 na sala 41F (60 minutos)  vídeo\nDescrição:  Apresentação do Objetivo do Programa:\n\nDotação de rede comunicação e TI nas escolas públicas, garantindo, com alto desempenho, acesso a conteúdo educa  tivo, cultural, profissionalizante e recreativo, de forma integrada e alinhada com as políticas do MEC, considerando a centralidade do professor e o estudante no processo educacional.",
    "favorite": "0",
    "length": "43:08",
    "likes": "0",
    "recorded": "2016-07-13",
    "speakers": [],
    "tags": [],
    "thumbnail_url": "https://i.ytimg.com/vi/sSJ8hA8pxOY/hqdefault.jpg",
    "title": "Programa Minha Escola Mais Inteligente",
    "videos": [
        {
            "code": "sSJ8hA8pxOY",
            "type": "youtube"
        }
    ],
    "views": "16"
}