{
    "description": "Inscreva-se.\nhttps://goo.gl/NfsjjA\n\nRobótica Educativa no Ensino Fundamental - Séries Iniciais - É possível?\nTrilha: Educação - Educação\nAutores:\nJocemar do Nasicmento mostrar currículo\nApresentação:\nDia 15 às 13:00 na sala 41C (60 minutos)  vídeo\nDescrição:  Um relato da Experiencia de Implantação de Robótica Educativa no Ensino Fundamental - Series Iniciais, realizado em 2 Escolas da Rede Municipal de Ens  ino, que usaram métodos e ferramentas diferentes para atingir objetivos similares.",
    "favorite": "0",
    "length": "27:45",
    "likes": "0",
    "recorded": "2016-07-13",
    "speakers": [],
    "tags": [],
    "thumbnail_url": "https://i.ytimg.com/vi/5qjjMuh3zWc/hqdefault.jpg",
    "title": "Robótica Educativa no Ensino Fundamental   Séries Iniciais   É possível 1",
    "videos": [
        {
            "code": "5qjjMuh3zWc",
            "type": "youtube"
        }
    ],
    "views": "9"
}