{
    "description": "Early Bird tickets are now on sale for Front-Trends 2017, May 24-26. Get'em while they last! https://2017.front-trends.com/ \n\nThe popularity of building web sites with static site generators is on the rise. Their reduced complexity, easier compliance, cheaper hosting, and other benefits are getting people\u2019s attention, but they do have limits.\n\nThis talk will explore how we can break through some of those limits with the use of a new breed of hosted tools and services. We\u2019ll look at practical examples of how a static site generator can help deliver a modern web development workflow, support a living styleguide, and also pack the kind of dynamic punch that you\u2019d only think possible from bigger application stacks.",
    "recorded": "2016-05-18",
    "speakers": ["phil-hawksworth"],
    "tags": [],
    "thumbnail_url": "https://i.ytimg.com/vi/_cuZcnJIjls/hqdefault.jpg",
    "title": "Static Sites go all Hollywood",
    "videos": [
        {
            "code": "_cuZcnJIjls",
            "type": "youtube"
        }
    ]
}