{"description": "Apache in Science", "event": {"name": "ApacheCon North America 2013", "nickname": "apachecon-na-2013", "twitter": "ApacheCon", "url": "http://na13.apachecon.com/"}, "favorite": "0", "file_date": "2016-12-03", "filename": "wengines-workflows-and-2-years-of-advanced-data-processing-in-apache-oodt", "length": "01:02:41", "likes": "2", "recorded": "2013-02-28", "short_description": "Apache in Science", "speaker_twitters": " @chrismattmann", "speakers": {"chris-mattmann": {"episodes": [], "hosting": [], "info": {"country": "Pasadena, CA, USA", "github": "chrismattmann", "home": "http://sunset.usc.edu/~mattmann/", "name": "Chris Mattmann", "twitter": "chrismattmann"}, "videos": [{"event": {"name": "ApacheCon North America 2013", "nickname": "apachecon-na-2013", "twitter": "ApacheCon", "url": "http://na13.apachecon.com/"}, "filename": "wengines-workflows-and-2-years-of-advanced-data-processing-in-apache-oodt-1fa453", "recorded": "2013-02-28", "thumbnail_url": "https://i.ytimg.com/vi/GZC3Zn3VXt8/hqdefault.jpg", "title": "Wengines, Workflows, and 2 years of advanced data processing in Apache OODT."}, {"event": {"name": "ApacheCon North America 2013", "nickname": "apachecon-na-2013", "twitter": "ApacheCon", "url": "http://na13.apachecon.com/"}, "filename": "wengines-workflows-and-2-years-of-advanced-data-processing-in-apache-oodt", "recorded": "2013-02-28", "thumbnail_url": "https://i.ytimg.com/vi/GZC3Zn3VXt8/hqdefault.jpg", "title": "Wengines, Workflows, and 2 years of advanced data processing in Apache OODT."}]}}, "tags": [], "thumbnail_url": "https://i.ytimg.com/vi/GZC3Zn3VXt8/hqdefault.jpg", "title": "Wengines, Workflows, and 2 years of advanced data processing in Apache OODT.", "tweet_video": "Wengines%2C%20Workflows%2C%20and%202%20years%20of%20advanced%20data%20processing%20in%20Apache%20OODT.%20https%3A//codeandtalk.com/v/apachecon-na-2013/wengines-workflows-and-2-years-of-advanced-data-processing-in-apache-oodt%20presented%20%40ApacheCon%20by%20%40chrismattmann", "videos": [{"code": "GZC3Zn3VXt8", "type": "youtube"}], "views": "75"}