{
    "abstract": "http://www.yapcna.org/yn2016/talk/6812",
    "description": "",
    "favorite": "0",
    "length": "51:42",
    "likes": "0",
    "recorded": "2016-06-20",
    "speakers": [
        "nicolas-rochelemagne"
    ],
    "tags": [],
    "thumbnail_url": "https://i.ytimg.com/vi/AMa1JWgG4yY/hqdefault.jpg",
    "title": "Perl dependencies: playing with %INC and profiling memory",
    "videos": [
        {
            "code": "AMa1JWgG4yY",
            "type": "youtube"
        }
    ],
    "views": "123"
}