{
    "description": "Spark et Cassandra sont des projets tr\u00e8s populaires, mais avez vous entendu parler d'Apache Zeppelin ? Zeppelin propose un syst\u00e8me de notebook pour pouvoir manipuler les donn\u00e9es de mani\u00e8re interactive. Zeppelin repose sur un syst\u00e8me de plugins qui permet de traiter des t\u00e2ches Spark, des requ\u00eates Spark SQL mais aussi des requ\u00eates CQL de Cassandra.\n\nJe montrerai comment construire un pipeline de transformation BigData en m\u00e9langeant du Spark, du Cassandra, du Shell, du Markdown, du ce-que-vous-voulez etc.\n\nVotre framework pr\u00e9f\u00e9r\u00e9 n'a pas encore de plugin pour Zeppelin ? Ecrivez-en un et partager le avec la communaut\u00e9!",
    "favorite": "0",
    "length": "33:09",
    "likes": "4",
    "recorded": "2016-04-20",
    "speakers": ["duyhai-doan"],
    "tags": [],
    "thumbnail_url": "https://i.ytimg.com/vi/eZyL61gMayE/hqdefault.jpg",
    "title": "Apache Zeppelin, un notebook d'avenir pour l'\u00e9co-syst\u00e8me Big Data",
    "videos": [
        {
            "code": "eZyL61gMayE",
            "type": "youtube"
        }
    ],
    "views": "395"
}