{
    "description": "Dans cette pr\u00e9sentation, je vous propose de d\u00e9couvrir ensemble d\u2019autre fa\u00e7on de d\u00e9velopper en Java et Java 8 en particulier, mais que peu ont test\u00e9. Est-il possible de limiter le nombre de sous-classes pour une classe ? Si on peut d\u00e9sormais mettre un comportement dans une interface, peut-on y mettre un \u00e9tat ? Et peut-on s\u00e9curiser la grammaire de ses DSL internes ? Live coding \u00e0 l\u2019appui, voici certaines des questions auxquelles nous allons essayer de r\u00e9pondre ou qu\u2019on ne devrait jamais aborder.",
    "favorite": "0",
    "length": "41:41",
    "likes": "10",
    "recorded": "2016-04-20",
    "speakers": [
        "francois-sarradin"
    ],
    "tags": [],
    "thumbnail_url": "https://i.ytimg.com/vi/evS3iwZLS4s/hqdefault.jpg",
    "title": "Java (8) eXperiments",
    "videos": [
        {
            "code": "evS3iwZLS4s",
            "type": "youtube"
        }
    ],
    "views": "1500"
,    "language" : "French"
}