{
    "accessibility": "",
    "cfp_end": "",
    "code_of_conduct": "https://www.codeonthebeach.com/about/terms",
    "comment": "",
    "diversitytickets": "",
    "diversitytickets_text": "",
    "diversitytickets_url": "",
    "event_end": "2018-08-12",
    "event_start": "2018-08-09",
    "facebook": "",
    "hashtag": "CodeOnTheBeach",
    "languages": [
        "English"
    ],
    "location": {
        "city": "Atlantic Beach",
        "country": "USA",
        "state": "Florida"
    },
    "name": "Code on the Beach",
    "tags": [],
    "twitter": "CodeOnTheBeach",
    "website": "https://www.codeonthebeach.com/",
    "youtube": ""
}