{
    "accessibility": "",
    "cfp_end": "",
    "code_of_conduct": "http://confcodeofconduct.com/",
    "diversitytickets": "",
    "event_end": "2015-11-06",
    "event_start": "2015-11-06",
    "facebook": "",
    "languages": [
        "English"
    ],
    "location": {
        "city": "Brighton",
        "country": "UK",
        "state": "England"
    },
    "name": "Full Frontal - ffconf",
    "tags": [
        "web",
        "css",
        "frontend"
    ],
    "twitter": "ffconf",
    "website": "https://2015.ffconf.org/",
    "youtube": "PLXmT1r4krsTqtLdWln2ritJZTjd5a06h2"
}