{
    "accessibility": "",
    "cfp_end": "",
    "code_of_conduct": "https://golang.org/conduct",
    "event_end": "2018-08-30",
    "event_start": "2018-08-27",
    "facebook": "https://www.facebook.com/gophercon/",
    "languages": [
        "English"
    ],
    "location": {
        "city": "Denver",
        "country": "USA",
        "state": "Colorado"
    },
    "name": "GopherCon Denver",
    "tags": [
        "go",
        "golang"
    ],
    "twitter": "GopherCon",
    "website": "https://gophercon.com/",
    "youtube": ""
}