{
    "accessibility": "",
    "cfp_end": "",
    "code_of_conduct": "http://confcodeofconduct.com/",
    "diversitytickets": "",
    "event_end": "2018-09-13",
    "event_start": "2018-09-12",
    "facebook": "https://www.facebook.com/JavaZoneConference",
    "languages": [
        "English"
    ],
    "location": {
        "city": "Oslo",
        "country": "Norway",
        "state": ""
    },
    "name": "JavaZone",
    "tags": [
        "java"
    ],
    "twitter": "javazone",
    "website": "https://2018.javazone.no/",
    "youtube": ""
}
