{
    "accessibility": "",
    "cfp_end": "",
    "code_of_conduct": "http://2018.jsunconf.eu/coc",
    "diversitytickets": "",
    "event_end": "2018-04-22",
    "event_start": "2018-04-21",
    "facebook": "",
    "languages": [
        "English"
    ],
    "location": {
        "city": "Hamburg",
        "country": "Germany",
        "state": ""
    },
    "name": "JSUnconf",
    "tags": [
        "javascript"
    ],
    "twitter": "jsunconf",
    "website": "http://2018.jsunconf.eu/",
    "youtube": ""
}
