{
    "accessibility": "",
    "cfp_end": "",
    "city": "Madrid",
    "code_of_conduct": "http://madrid.pm.org/workshop/page/code-of-conduct.html",
    "country": "Spain",
    "diversitytickets": "",
    "event_end": "2017-06-03",
    "event_start": "2017-06-03",
    "facebook": "",
    "hashtag": "",
    "languages": "English",
    "name": "Madrid Perl Workshop 2017",
    "state": "",
    "topics": "Perl",
    "twitter": "PerlMadrid",
    "url": "http://madrid.pm.org/workshop/",
    "youtube": ""
}