{
    "accessibility": "",
    "cfp_end": "",
    "code_of_conduct": "https://2018.syntaxcon.com/about/code-of-conduct/",
    "diversitytickets": "",
    "event_end": "2018-06-08",
    "event_start": "2018-06-06",
    "facebook": "",
    "languages": [
        "English"
    ],
    "location": {
        "city": "North Charleston",
        "country": "USA",
        "state": "South Carolina"
    },
    "name": "Syntax Code & Craft Convention 2018",
    "tags": [
        "frontend",
        "full-stack"
    ],
    "twitter": "syntaxcon",
    "website": "https://2018.syntaxcon.com/",
    "youtube": ""
}