{
    "description": "This talk will focus more on the delivery aspects of sending lots of email while including some basic configuration for Linux, Rails, & Postfix.\n\nHow to send lots of email and not look like spam.\nWhat You Don't Know About Sending Email\nMost People Who Send Lots of Email, are Sending Spam.\nMake Sure You're not Sending Spam\nMake Sure the Gatekeepers you're Sending to Know Who You Are\nMake Sure You're Using the Right Tools for the Job\nGather Feedback From the People You are Sending to, and Act on it\nHow to comfortably forget most of what I said here (except for the not sending spam part)\nHelpful Links\n\nShot by Just Shoot Me Digital - http://www.jsmdigital.co.za/\nMusic is Coma's U Dub by Nokom electro - http://www.jamendo.com/en/track/39238/coma-s-u-dub",
    "favorite": "0",
    "length": "33:57",
    "likes": "0",
    "recorded": "2014-02-06",
    "speakers": [
        "sally-lehman"
    ],
    "tags": [],
    "thumbnail_url": "https://i.ytimg.com/vi/XtGUd174n5A/hqdefault.jpg",
    "title": "Email Delivery for Rails Folks",
    "videos": [
        {
            "code": "XtGUd174n5A",
            "type": "youtube"
        }
    ],
    "views": "65"
}