{
    "description": "Shot by Just Shoot Me Digital - http://www.jsmdigital.co.za/\nMusic is Coma's U Dub by Nokom electro - http://www.jamendo.com/en/track/39238/coma-s-u-dub",
    "favorite": "0",
    "length": "24:46",
    "likes": "1",
    "recorded": "2014-02-06",
    "speakers": [],
    "tags": [],
    "thumbnail_url": "https://i.ytimg.com/vi/jvRjtfqg7q0/hqdefault.jpg",
    "title": "Google APIs for Ruby on Ruby on Rails on Google Compute Engine - Daniel Acton",
    "videos": [
        {
            "code": "jvRjtfqg7q0",
            "type": "youtube"
        }
    ],
    "views": "2475"
}