{"description": "Speaker: Sara Itani https://twitter.com/mousetraps\nwww.nodeconf.eu \nNodeConfEU 2016.\nLyrath Estate, Kilkenny, Ireland.", "event": {"name": "NodeConf EU 2016", "nickname": "nodeconf-eu-2016", "twitter": "NodeConfEU", "url": "http://www.nodeconf.eu/"}, "favorite": "0", "file_date": "2016-12-03", "filename": "nodeconf-eu-node-js-microsoft-a-love-story-about-developer-tools-sara-itani", "length": "38:29", "likes": "1", "recorded": "2016-10-16", "short_description": "Speaker: Sara Itani https://twitter.com/mousetraps www.nodeconf.eu NodeConfEU 2016. Lyrath Estate, Kilkenny, Ireland.", "speaker_twitters": " @mousetraps", "speakers": {"sara-itani": {"episodes": [], "hosting": [], "info": {"country": "Seattle, WA, USA", "github": "mousetraps", "home": "http://saraitani.com/", "name": "Sara Itani", "twitter": "mousetraps"}, "videos": [{"event": {"name": "NodeConf EU 2016", "nickname": "nodeconf-eu-2016", "twitter": "NodeConfEU", "url": "http://www.nodeconf.eu/"}, "filename": "nodeconf-eu-node-js-microsoft-a-love-story-about-developer-tools-sara-itani", "recorded": "2016-10-16", "thumbnail_url": "https://i.ytimg.com/vi/UHKFmHoyVF0/hqdefault.jpg", "title": "Node js & Microsoft: A love story about developer tools"}]}}, "tags": [], "thumbnail_url": "https://i.ytimg.com/vi/UHKFmHoyVF0/hqdefault.jpg", "title": "Node js & Microsoft: A love story about developer tools", "tweet_video": "Node%20js%20%26%20Microsoft%3A%20A%20love%20story%20about%20developer%20tools%20https%3A//codeandtalk.com/v/nodeconf-eu-2016/nodeconf-eu-node-js-microsoft-a-love-story-about-developer-tools-sara-itani%20presented%20%40NodeConfEU%20by%20%40mousetraps", "videos": [{"code": "UHKFmHoyVF0", "type": "youtube"}], "views": "91"}