{
    "abstract": "https://events.drupal.org/dublin2016/sessions/cdn-and-beyond-speed-websites-beyond-us-and-europe",
    "description": "Us web geeks strive for one thing when it comes to performance: fast and reliable websites all the time, everywhere.\n\nNo matter if you are connected via mobile networks or your super fast 1 GB/s fiber connection, when it comes to performance, it's easy to measure and optimize for one country. But what if your user base is global? How do you ensure speed across the globe?\n\nFor starters, global means more than just Europe and the States.  \n\nSure you can get along fine using well known CDN solutions that work across the Americas and Europe, but if you need to enter global markets like China, your requirements get infinitely more complicated.\n\nIn this session I’ll cover: \n\nInternational vendors and what your options are \nHow other countries work in terms of peering and pricing policy\nHow to get a server in China (and why you need your customer for that)\nThe different CDN approaches which play nice with Drupal\nAttend this session if:\n\nYou want to get your sites up to speed in different countries \nYou already know how to use CDNs but still think “there must be more”\nYou want know which hoops you need to jump through to host your site in a restrictive internet environment",
    "favorite": "0",
    "length": "37:30",
    "likes": "1",
    "recorded": "2016-09-26",
    "speakers": [
        "bastian-widmer"
    ],
    "tags": [],
    "thumbnail_url": "https://i.ytimg.com/vi/zBbzuit2IoA/hqdefault.jpg",
    "title": "To CDN and beyond! Speed up websites beyond the US and Europe",
    "videos": [
        {
            "code": "zBbzuit2IoA",
            "type": "youtube"
        }
    ],
    "views": "84"
}