{
    "description": "Vert.x est une plateforme pour créer des applications concurrentes, performantes et polyglottes sur la JVM. Cette session parlera des choix faits par Vert.x, de son modèle de concurrence et explique comment écrire des applications concurrentes et performantes de manière très simple. Nous aborderons quelques aspects clés de Vert.x comme le bus d'évènement distribué ou la haute disponibilité. La présentation parlera de Vert.x 3.0, de ses nouvelles fonctionnalités et montrera des exemples dans plusieurs languages tels que Java, Javascript, Groovy ou Ruby.\n\n\nAuthor:\n Julien Viet\nJulien is passionate about open source and development. He has been developing Open Source software for more than 10 years. He is currently employed by Red Hat as contributor of the Vert.x project.",
    "favorite": "0",
    "length": "57:03",
    "likes": "0",
    "recorded": "2015-04-09",
    "speakers": [
        "julien-viet"
    ],
    "tags": [],
    "thumbnail_url": "https://i.ytimg.com/vi/1lCfVm82eRg/hqdefault.jpg",
    "title": "Applications Concurrentes Polyglottes avec Vert.x",
    "videos": [
        {
            "code": "1lCfVm82eRg",
            "type": "youtube"
        }
    ],
    "views": "51"
}