{
  "description": "http://www.CityTV.nl\nhttp://www.t-dose.org/\nPlaylist T-Dose 2007\nhttp://www.youtube.com/playlist?list=PLBZBIkixHEieGLtIxfaL1y1QPBLTUSegB\n\n(Keynote) Knut Yrving\nFree Software in telecom\n\nFree software in Telecom - keynote\nCommunity Manager Knut Yrvin at Trolltech will present mobile phone programming with Qt on Qtopia Greenphone. He will focus on game programming and Telenors Program for Advanced Telecom Services. \n\nMore at\nhttp://www.t-dose.org/2007/speakers:\n\nTechnical Dutch Open Source Event.\nOctober 13, 2007\nFontys Eindhoven.",
  "recorded": "2007-10-13",
  "speakers": [],
  "tags": [],
  "thumbnail_url": "https://i.ytimg.com/vi/Sg-sMQscx_g/hqdefault.jpg",
  "title": "T-DOSE 2007, Free Software in telecom, (Keynote) Knut Yrving",
  "videos": [
    {
      "code": "Sg-sMQscx_g",
      "type": "youtube"
    }
  ]
}