{"description": "Download video: http://videos.fscons.org/fscons/2013/c444_-_2013-11-10_1000_-_wp_global_-_eric_luth_-_62.ogv", "event": {"name": "FSCONS 2013", "nickname": "fscons-2013", "twitter": "fscons", "url": "https://fscons.org/2013/"}, "favorite": "0", "file_date": "2016-12-03", "filename": "eric-luth-wpglobal", "length": "40:43", "likes": "0", "recorded": "2013-11-08", "short_description": "Download video: http://videos.fscons.org/fscons/2013/c444_-_2013-11-10_1000_-_wp_global_-_eric_luth_-_62.ogv", "speaker_twitters": "", "speakers": {}, "tags": [], "thumbnail_url": "https://i.ytimg.com/vi/Ujrrt8X5sno/hqdefault.jpg", "title": "Eric Luth: WP:Global?", "tweet_video": "Eric%20Luth%3A%20WP%3AGlobal%3F%20https%3A//codeandtalk.com/v/fscons-2013/eric-luth-wpglobal%20presented%20%40fscons", "videos": [{"code": "Ujrrt8X5sno", "type": "youtube"}], "views": "37"}