{
    "description": "Persönliche Daten durch E-Mailverschlüsselung schützen\n\nWürden sie vertrauliche Informationen auf eine Postkarte schreiben? Eine normale E-Mail ist mit einer Postkarte zu vergleichen, die jeder mitlesen kann. Ein Werkzeug, um Persönliches zu schützen, ist GnuPG (Gnu Privacy Guard), eine freie Software zur E-Mailverschlüsselung.\n\nhttp://glt13-programm.linuxtage.at/events/173.de.html",
    "favorite": "0",
    "length": "44:57",
    "likes": "2",
    "recorded": "2013-04-20",
    "speakers": [
        "lukas-prokop"
    ],
    "tags": [],
    "thumbnail_url": "https://i.ytimg.com/vi/ECe3dMXsDfg/hqdefault.jpg",
    "title": "GnuPG",
    "videos": [
        {
            "code": "ECe3dMXsDfg",
            "type": "youtube"
        }
    ],
    "views": "511"
}