{
    "abstract": "https://events.drupal.org/neworleans2016/sessions/delivering-business-results-beyond-revenue",
    "description": "Drupal is known as a flexible, scalable and cost efficient open source CMS used by both small businesses and large enterprise organizations to rapidly deploy content to consumers. GE Energy Connections Digital Strategy Leader, Holly Bounds and FFW’s Brent Bice will discuss how Drupal not only generates traffic, conversion and increased revenue, but provides intrinsic value to organizations through:\n\n· Reduced support and maintenance costs\n· Improved internal collaboration\n· Increased productivity\n\nLearn how Drupal delivers business results beyond clicks, conversions and revenue.",
    "favorite": "0",
    "length": "59:23",
    "likes": "0",
    "recorded": "2016-05-09",
    "speakers": [
        "brent-bice"
    ],
    "tags": [],
    "thumbnail_url": "https://i.ytimg.com/vi/rzwYw8wo92M/hqdefault.jpg",
    "title": "DrupalCon New Orleans 2016: GE Energy Connections & FFW",
    "videos": [
        {
            "code": "rzwYw8wo92M",
            "type": "youtube"
        }
    ],
    "views": "226"
}