{
    "description": "ApacheCon NA 2015 - Comcast VIPER: We Watch TV at Work - Neill A. Kipp, Distinguished Engineer, Comcast",
    "favorite": "0",
    "length": "06:35",
    "likes": "4",
    "recorded": "2015-04-13",
    "speakers": [],
    "tags": [],
    "thumbnail_url": "https://i.ytimg.com/vi/oDcKRDftIh4/hqdefault.jpg",
    "title": "Comcast VIPER: We Watch TV at Work - Neill A. Kipp, Distinguished Engineer, Comcast",
    "videos": [
        {
            "code": "oDcKRDftIh4",
            "type": "youtube"
        }
    ],
    "views": "404"
}