{"description": "", "event": {"name": "RubyConf India 2016", "nickname": "rubyconf-india-2016", "twitter": "rubyconfindia", "url": "https://github.com/rubyconfindia/rci2016"}, "favorite": "0", "file_date": "2016-12-03", "filename": "rubyconf-india-2016-anatomy-of-constant-lookup-and-autoloading-in-rails-by-prathamesh-sonpatki", "length": "32:24", "likes": "2", "recorded": "2016-03-19", "short_description": "", "speaker_twitters": " @_cha1tanya", "speakers": {"prathamesh-sonpatki": {"episodes": [], "hosting": [], "info": {"country": "Pune, India", "github": "prathamesh-sonpatki", "name": "Prathamesh Sonpatki", "twitter": "_cha1tanya"}, "videos": [{"event": {"name": "RailsConf 2016", "nickname": "railsconf-2016", "twitter": "railsconf", "url": "http://railsconf.com/2016"}, "filename": "railsconf-2016-secrets-of-testing-rails-5-apps-by-prathamesh-sonpatki", "recorded": "2016-05-04", "thumbnail_url": "https://i.ytimg.com/vi/_qG7A9LxBPw/hqdefault.jpg", "title": "Secrets of Testing Rails 5 apps"}, {"event": {"name": "RubyConf India 2016", "nickname": "rubyconf-india-2016", "twitter": "rubyconfindia", "url": "https://github.com/rubyconfindia/rci2016"}, "filename": "rubyconf-india-2016-anatomy-of-constant-lookup-and-autoloading-in-rails-by-prathamesh-sonpatki", "recorded": "2016-03-19", "thumbnail_url": "https://i.ytimg.com/vi/F_B8vKp6suE/hqdefault.jpg", "title": "Anatomy of constant lookup and autoloading in Rails"}]}}, "tags": [{"link": "ruby", "text": "Ruby"}, {"link": "rails", "text": "Rails"}], "thumbnail_url": "https://i.ytimg.com/vi/F_B8vKp6suE/hqdefault.jpg", "title": "Anatomy of constant lookup and autoloading in Rails", "tweet_video": "Anatomy%20of%20constant%20lookup%20and%20autoloading%20in%20Rails%20https%3A//codeandtalk.com/v/rubyconf-india-2016/rubyconf-india-2016-anatomy-of-constant-lookup-and-autoloading-in-rails-by-prathamesh-sonpatki%20presented%20%40rubyconfindia%20by%20%40_cha1tanya%20%23ruby%20%23rails", "videos": [{"code": "F_B8vKp6suE", "type": "youtube"}], "views": "204"}