{
    "description": "Easier debugging, improved testability, simpler code. All these are great benefits of the functional programming encouraged by the Elm programming language. But what if you could get these same benefits in your plain old javascript code! This talk will introduce developers to the key concepts of functional programming as facilitated by Elm, and their counterparts in ES5. By the end of the talk, developers will know how to how write functional JS code with all the benefits of Elm code.",
    "favorite": "0",
    "length": "28:46",
    "likes": "6",
    "recorded": "2016-04-15",
    "speakers": [
        "juan-caicedo"
    ],
    "tags": [],
    "thumbnail_url": "https://i.ytimg.com/vi/UmxPZpam7o0/hqdefault.jpg",
    "title": "ELM  JAVASCRIPT, HOW TO ENJOY FUNCTIONAL PROGRAMMING IN ES5",
    "videos": [
        {
            "code": "UmxPZpam7o0",
            "type": "youtube"
        }
    ],
    "views": "355"
}