{"episodes": [], "hosting": [], "info": {"country": "Palo Alto, CA, USA", "github": "alansouzati", "home": "https://www.linkedin.com/in/alansouzati", "name": "Alan Souza", "twitter": "alansouzati"}, "videos": [{"event": {"name": "JSConf Uruguay 2016", "nickname": "jsconf-uruguay-2016", "twitter": "JSConfUY", "url": "https://jsconf.uy/"}, "filename": "alan-souza-reactjs-tips-and-tricks-to-create-accessible-svg-components", "recorded": "2016-04-15", "thumbnail_url": "https://i.ytimg.com/vi/Qo0BHIkKzqo/hqdefault.jpg", "title": "REACTJS: TIPS AND TRICKS TO CREATE ACCESSIBLE SVG COMPONENTS"}]}