{"episodes": [], "hosting": [], "info": {"country": "USA", "github": "ModulesUnraveled", "home": "https://modulesunraveled.com/", "name": "Brian Lewis", "twitter": "ModsUnraveled"}, "videos": [{"event": {"name": "DrupalCon New Orleans 2016", "nickname": "drupalcon-new-orleans-2016", "twitter": "drupalconNA", "url": "https://events.drupal.org/neworleans2016"}, "filename": "drupalcon-new-orleans-2016-configuration-management-composer-git-and-drush-in-drupal-8", "recorded": "2016-05-09", "thumbnail_url": "https://i.ytimg.com/vi/1bxQJtiHy4k/hqdefault.jpg", "title": "Configuration Management, Composer, Git and Drush in Drupal 8"}]}