{"episodes": [], "hosting": [], "info": {"country": "Sri Lanka", "github": "dilumn", "home": "http://dilumn.github.io/", "name": "Dilum Navanjana", "twitter": "dilumn_"}, "videos": [{"event": {"name": "Deccan RubyConf 2015", "nickname": "deccanrubyconf-2015", "twitter": "deccanrubyconf", "url": "http://lanyrd.com/2015/drbc2015/"}, "filename": "concurrent-ruby-with-celluloid-dilum-navanjana", "recorded": "2015-08-08", "thumbnail_url": "https://i.ytimg.com/vi/U4oeH-3za1M/hqdefault.jpg", "title": "Concurrent Ruby with Celluloid"}]}