{"episodes": [], "hosting": [], "info": {"city": "Prague", "country": "Czech Republic", "github": "choroba", "name": "E. Choroba", "twitter": "e_choroba"}, "videos": [{"event": {"name": "YAPC - European Perl Conference 2016", "nickname": "yapc-eu-2016", "twitter": "yapceu", "url": "http://act.yapc.eu/ye2016/"}, "filename": "choroba-karel-educational-programming-language-yapceurope-2016", "recorded": "2016-08-24", "thumbnail_url": "https://i.ytimg.com/vi/rhoM2gQQy7M/hqdefault.jpg", "title": "Karel, Educational programming language"}]}