{"episodes": [], "hosting": [], "info": {"country": "Taipei, Taiwan", "github": "gsklee", "home": "http://gsklee.im/about", "name": "G. Kay Lee", "twitter": "gsklee"}, "videos": [{"event": {"name": "JSConf Asia 2015", "nickname": "jsconf-asia-2015", "twitter": "jsconfasia", "url": "https://2015.jsconf.asia/"}, "filename": "g-kay-lee-bio-inspired-frontend-engineering-jsconfasia-2015", "recorded": "2015-11-19", "thumbnail_url": "https://i.ytimg.com/vi/D2o005ucV30/hqdefault.jpg", "title": "Bio-Inspired Frontend Engineering"}]}