{"episodes": [], "hosting": [], "info": {"country": "Eugene, OR, USA", "home": "http://adunumdatum.org/", "name": "Jacob Levernier"}, "videos": [{"event": {"name": "Linuxfest Northwest 2016", "nickname": "linuxfest-northwest-2016", "twitter": "", "url": "https://www.linuxfestnorthwest.org/2016"}, "filename": "linuxfest-northwest-2016-building-book-scanners-without-breaking-the-bank", "recorded": "2016-04-23", "thumbnail_url": "https://i.ytimg.com/vi/1TMRzyy7zVE/hqdefault.jpg", "title": "Building Book Scanners without Breaking the Bank"}]}