{"episodes": [], "hosting": [], "info": {"country": "Estonia", "github": "karltiirik", "home": "https://www.linkedin.com/in/karltiirik", "name": "Karl Tiirik", "twitter": "MrTiirik"}, "videos": [{"event": {"name": "Nordic Testing Days 2016", "nickname": "nordictestingdays-2016", "twitter": "nordictestdays", "url": "http://nordictestingdays.eu/archive/2016"}, "filename": "nordic-testing-days-2016-interview-5", "recorded": "2016-06-01", "thumbnail_url": "https://i.ytimg.com/vi/jUobO_gY3pE/hqdefault.jpg", "title": "Interview with Karl Tiirik"}]}