{"episodes": [], "hosting": [], "info": {"country": "Paris, France", "github": "MattiSG", "home": "https://mattischneider.fr/", "name": "Matti Schneider", "twitter": "matti_sg"}, "videos": [{"event": {"name": "Devoxx France 2016", "nickname": "devoxx-france-2016", "twitter": "DevoxxFR", "url": "http://www.devoxx.fr/"}, "filename": "action-publique-et-numerique-matti-schneider", "recorded": "2016-04-20", "thumbnail_url": "https://i.ytimg.com/vi/qAFm3HhoZNI/hqdefault.jpg", "title": "Action publique et Num\u00e9rique"}]}