{"episodes": [], "hosting": [], "info": {"country": "Leiden, The Nethelands", "github": "mhelvens", "home": "http://www.mhelvens.net/", "name": "Michiel Helvensteijn", "twitter": "mhelvens"}, "videos": [{"event": {"name": "ngEurope 2014", "nickname": "ng-europe-2015", "twitter": "ngEurope", "url": "https://2015.ngeurope.org/"}, "filename": "feature-oriented-programming-with-deltajs-by-michiel-helvensteijn-at-ng-europe-2014", "recorded": "2014-10-22", "thumbnail_url": "https://i.ytimg.com/vi/4pnGM3l2O5Q/hqdefault.jpg", "title": "Feature-oriented programming with delta.js"}]}