{"episodes": [], "hosting": [], "info": {"country": "Zurich, Switzerland", "github": "Schnitzel", "home": "http://schnitzel.io/", "name": "Michael Schmid", "twitter": "Schnitzel"}, "videos": [{"event": {"name": "DrupalCon Dublin 2016", "nickname": "drupalcon-dublin-2016", "twitter": "drupalconeur", "url": "https://events.drupal.org/dublin2016"}, "filename": "drupalcon-dublin-2016-drupal-security-there-is-a-mini-drupalgeddon", "recorded": "2016-09-26", "thumbnail_url": "https://i.ytimg.com/vi/ej8yiPHota4/hqdefault.jpg", "title": "Drupal Security: There is a Mini-DrupalGeddon"}]}