{"episodes": [], "hosting": [], "info": {"country": "Warsaw, Poland", "github": "chastell", "home": "http://chastell.net/", "name": "Piotr Szotkowski", "twitter": "chastell"}, "videos": [{"event": {"name": "Ruby Conf Portugal", "nickname": "rubyconf-portugal-2016", "twitter": "rubyconfpt", "url": "http://rubyconf.pt/"}, "filename": "piotr-szotkowski-they-hear-me-typin-they-hatin-rubyconf-portugal16", "recorded": "2016-10-27", "thumbnail_url": "https://i.ytimg.com/vi/y9yQPl2WxfQ/hqdefault.jpg", "title": "They Hear Me Typin\u2019, They Hatin\u2019"}]}