{"episodes": [], "hosting": [], "info": {"country": "Chicago, IL, USA", "github": "rmw", "home": "http://www.rebeccamiller-webster.com/", "name": "Rebecca Miller-Webster", "twitter": "rmillerwebster"}, "videos": [{"event": {"name": "RailsConf 2016", "nickname": "railsconf-2016", "twitter": "railsconf", "url": "http://railsconf.com/2016"}, "filename": "railsconf-2016-frameworks-for-feedback-by-rebecca-miller-webster", "recorded": "2016-05-04", "thumbnail_url": "https://i.ytimg.com/vi/q8K_66PA2qw/hqdefault.jpg", "title": "Frameworks for Feedback"}]}