{"episodes": [], "hosting": [], "info": {"country": "Antwerp, Belgium", "github": "SilVdB", "home": "http://silvdb.github.io/", "name": "Silke Van den Broeck", "twitter": "Silvdb"}, "videos": [{"event": {"name": "Refresh 2015", "nickname": "refresh-2015", "twitter": "REFRESHRocks", "url": "http://2015.refresh.rocks/"}, "filename": "refresh-2015-silke-van-den-broeck-modular-development-the-neoscores-way", "recorded": "2015-09-04", "thumbnail_url": "https://i.ytimg.com/vi/epelMxfdqdQ/hqdefault.jpg", "title": "Modular development, the neoScores way"}]}