{"episodes": [], "hosting": [], "info": {"country": "Pune, India", "github": "yogeshsajanikar", "name": "Yogesh Sajanikar", "twitter": "yogeshsajanikar"}, "videos": [{"event": {"name": "Functional Conf 2016", "nickname": "functionalconf-2016", "twitter": "fnConf", "url": "http://functionalconf.com/2016/"}, "filename": "implementing-spark-like-system-in-haskell-by-yogesh-sajanikar", "recorded": "2016-10-13", "thumbnail_url": "https://i.ytimg.com/vi/o6XddljM3nI/hqdefault.jpg", "title": "Implementing Spark like system in Haskell"}]}